lasso/__init__.py
lasso/issues/VERSION.txt
lasso/issues/__init__.py
lasso/issues/argparse.py
lasso/issues/github.py
lasso/issues/issues/RstRddReport.py
lasso/issues/issues/__init__.py
lasso/issues/issues/add_version_label_to_open_bugs.py
lasso/issues/issues/issues.py
lasso/issues/issues/labels.py
lasso/issues/issues/move_issues.py
lasso/issues/issues/utils.py
lasso/issues/milestones/__init__.py
lasso/issues/milestones/milestones.py
lasso_issues-2.0.0.dist-info/licenses/LICENSE.md
lasso_issues-2.0.0.dist-info/licenses/NOTICE.txt
lasso_issues-2.0.0.dist-info/METADATA
lasso_issues-2.0.0.dist-info/WHEEL
lasso_issues-2.0.0.dist-info/entry_points.txt
lasso_issues-2.0.0.dist-info/top_level.txt
lasso_issues-2.0.0.dist-info/zip-safe
lasso_issues-2.0.0.dist-info/RECORD
