Metadata-Version: 2.4
Name: lasso.issues
Version: 2.0.0
Summary: Issue handling for the Planetary Data System
Home-page: https://github.com/NASA-PDS/lasso-issues
Download-URL: https://github.com/NASA-PDS/lasso-issues/releases/
Author: PDS
Author-email: pds_operator@jpl.nasa.gov
License: apache-2.0
Keywords: pds,planetary data,ci,automation,issues
Classifier: Programming Language :: Python :: 3
Classifier: Programming Language :: Python :: 3.13
Classifier: Operating System :: OS Independent
Requires-Python: >=3.13
License-File: LICENSE.md
License-File: NOTICE.txt
Requires-Dist: github3.py==4.0.1
Requires-Dist: rstcloth~=0.6.0
Requires-Dist: pyzenhub~=0.3.2
Requires-Dist: mdutils~=1.8.0
Requires-Dist: pandas==2.3.0
Provides-Extra: dev
Requires-Dist: black~=23.7.0; extra == "dev"
Requires-Dist: flake8~=6.1.0; extra == "dev"
Requires-Dist: flake8-bugbear~=23.7.10; extra == "dev"
Requires-Dist: flake8-docstrings~=1.7.0; extra == "dev"
Requires-Dist: pep8-naming~=0.13.3; extra == "dev"
Requires-Dist: mypy~=1.5.1; extra == "dev"
Requires-Dist: pydocstyle~=6.3.0; extra == "dev"
Requires-Dist: coverage~=7.3.0; extra == "dev"
Requires-Dist: pytest~=7.4.0; extra == "dev"
Requires-Dist: pytest-cov~=4.1.0; extra == "dev"
Requires-Dist: pytest-watch~=4.2.0; extra == "dev"
Requires-Dist: pytest-xdist~=3.3.1; extra == "dev"
Requires-Dist: pre-commit~=3.3.3; extra == "dev"
Requires-Dist: sphinx~=8.2.3; extra == "dev"
Requires-Dist: sphinx-rtd-theme~=3.0.2; extra == "dev"
Requires-Dist: sphinxcontrib-applehelp~=2.0.0; extra == "dev"
Requires-Dist: sphinxcontrib-devhelp~=2.0.0; extra == "dev"
Requires-Dist: sphinxcontrib-htmlhelp~=2.1.0; extra == "dev"
Requires-Dist: sphinxcontrib.serializinghtml~=2.0.0; extra == "dev"
Requires-Dist: sphinxcontrib.qthelp~=2.0.0; extra == "dev"
Requires-Dist: alabaster~=1.0.0; extra == "dev"
Requires-Dist: tox~=4.11.0; extra == "dev"
Requires-Dist: types-setuptools~=68.1.0.0; extra == "dev"
Requires-Dist: Jinja2~=3.1.6; extra == "dev"
Dynamic: download-url
Dynamic: license-file
